hestia/__init__.py
hestia/auth.py
hestia/bool_utils.py
hestia/cached_property.py
hestia/crypto.py
hestia/date_formatter.py
hestia/date_utils.py
hestia/datetime_typing.py
hestia/ephemeral_services.py
hestia/exceptions.py
hestia/fs.py
hestia/hashing.py
hestia/headers.py
hestia/http.py
hestia/humanize.py
hestia/imports.py
hestia/internal_services.py
hestia/list_utils.py
hestia/logging_utils.py
hestia/manager_interface.py
hestia/memoize_decorators.py
hestia/np_utils.py
hestia/paths.py
hestia/service_interface.py
hestia/signal_decorators.py
hestia/string_utils.py
hestia/tz_utils.py
hestia/units.py
hestia/unknown.py
hestia/urls_utils.py
hestia/user_path.py
tests/__init__.py
tests/test_humanize.py
tests/test_list_utils.py
tests/test_logging_utils.py
tests/test_memoize.py
tests/test_units.py
hestia-0.6.0.dist-info/LICENSE
hestia-0.6.0.dist-info/METADATA
hestia-0.6.0.dist-info/WHEEL
hestia-0.6.0.dist-info/top_level.txt
hestia-0.6.0.dist-info/RECORD
